rds_data_dao/__init__.py
rds_data_dao/db_util.py
rds_data_dao-0.1.1.dist-info/LICENSE.txt
rds_data_dao-0.1.1.dist-info/METADATA
rds_data_dao-0.1.1.dist-info/WHEEL
rds_data_dao-0.1.1.dist-info/top_level.txt
rds_data_dao-0.1.1.dist-info/RECORD
