Metadata-Version: 2.1
Name: rds-data-dao
Version: 0.1.1
Summary: RDS Data API Wrapper
Home-page: https://github.com/stavvy/rds-data-dao
Author: Chris Buonocore
Author-email: chris@stavvy.com
License: MIT
Platform: UNKNOWN
